README.txt
setup.cfg
setup.py
./README.txt
./setup.cfg
./setup.py
./docs/HISTORY.txt
./docs/INSTALL.txt
./docs/LICENSE.GPL
./docs/LICENSE.txt
./docs/README.txt
./on/__init__.py
./on/sales/README.txt
./on/sales/__init__.py
./on/sales/config.py
./on/sales/configure.zcml
./on/sales/interfaces.py
./on/sales/mail.txt
./on/sales/salesagent.py
./on/sales/salesagentproxy.py
./on/sales/salesarea.py
./on/sales/browser/__init__.py
./on/sales/browser/configure.zcml
./on/sales/browser/laender.gif
./on/sales/browser/sales.css
./on/sales/browser/salesagent.gif
./on/sales/browser/salesagent.pt
./on/sales/browser/salesagent.py
./on/sales/browser/salesagentproxy.pt
./on/sales/browser/salesagentproxy.py
./on/sales/browser/salesarea.gif
./on/sales/browser/salesarea.pt
./on/sales/browser/salesarea.py
./on/sales/browser/salesarea_details.pt
./on/sales/browser/salesmail.pt
./on/sales/browser/salesmail.py
./on/sales/browser/images/Flugpost-k.gif
./on/sales/browser/images/brief_icon.gif
./on/sales/browser/images/icon-magnifier-1.gif
./on/sales/browser/images/icon-magnifier-2.gif
./on/sales/browser/images/icon-qmark-1.gif
./on/sales/browser/images/icon-qmark-2.gif
./on/sales/browser/images/laender.gif
./on/sales/locales/on.sales.pot
./on/sales/locales/de/LC_MESSAGES/on.sales.po
./on/sales/locales/en/LC_MESSAGES/on.sales.po
./on/sales/locales/fr/LC_MESSAGES/on.sales.po
./on/sales/profiles/default/catalog.xml
./on/sales/profiles/default/factorytool.xml
./on/sales/profiles/default/metadata.xml
./on/sales/profiles/default/rolemap.xml
./on/sales/profiles/default/types.xml
./on/sales/profiles/default/types/SalesAgent.xml
./on/sales/profiles/default/types/SalesAgentProxy.xml
./on/sales/profiles/default/types/SalesArea.xml
./on/sales/proxy/salesagentproxy.py
./on/sales/tests/__init__.py
./on/sales/tests/base.py
./on/sales/tests/test_doctest.py
./on/sales/tests/test_setup.py
on/__init__.py
on.sales.egg-info/PKG-INFO
on.sales.egg-info/SOURCES.txt
on.sales.egg-info/dependency_links.txt
on.sales.egg-info/entry_points.txt
on.sales.egg-info/namespace_packages.txt
on.sales.egg-info/not-zip-safe
on.sales.egg-info/requires.txt
on.sales.egg-info/top_level.txt
on/sales/__init__.py
on/sales/config.py
on/sales/interfaces.py
on/sales/salesagent.py
