Metadata-Version: 1.0
Name: on.sales
Version: 0.4
Summary: present a sales organisation to users
Home-page: http://www.oeko.net
Author: Oeko.neT Mueller & Brandt GbR
Author-email: support@oeko.net
License: GPL
Platform: UNKNOWN
Classifier: Framework :: Plone
Classifier: Framework :: Zope2
Classifier: Framework :: Zope3
Classifier: Programming Language :: Python
Classifier: Topic :: Software Development :: Libraries :: Python Modules
